libname/__init__.py
libname/hello.py
Hellopckgyt-0.0.1.dist-info/METADATA
Hellopckgyt-0.0.1.dist-info/WHEEL
Hellopckgyt-0.0.1.dist-info/top_level.txt
Hellopckgyt-0.0.1.dist-info/RECORD
